sudalTest_v2/bmi_test.py
sudalTest_v2-0.0.0.2.dist-info/METADATA
sudalTest_v2-0.0.0.2.dist-info/WHEEL
sudalTest_v2-0.0.0.2.dist-info/top_level.txt
sudalTest_v2-0.0.0.2.dist-info/RECORD
